tests/__init__.py
tests/base.py
tests/test_api.py
tests/test_book.py
the_one_api_sdk/__init__.py
the_one_api_sdk/the_one_api.py
the_one_api_sdk/book/__init__.py
the_one_api_sdk/book/api.py
the_one_api_sdk/book/model.py
the_one_api_sdk/chapter/__init__.py
the_one_api_sdk/chapter/api.py
the_one_api_sdk/chapter/model.py
the_one_api_sdk/character/__init__.py
the_one_api_sdk/character/api.py
the_one_api_sdk/character/model.py
the_one_api_sdk/common/__init__.py
the_one_api_sdk/common/api_client.py
the_one_api_sdk/common/base.py
the_one_api_sdk/common/errors.py
the_one_api_sdk/movie/__init__.py
the_one_api_sdk/movie/api.py
the_one_api_sdk/movie/model.py
the_one_api_sdk/quote/__init__.py
the_one_api_sdk/quote/api.py
the_one_api_sdk/quote/model.py
michael_sdk-0.0.2.dist-info/LICENSE
michael_sdk-0.0.2.dist-info/METADATA
michael_sdk-0.0.2.dist-info/WHEEL
michael_sdk-0.0.2.dist-info/top_level.txt
michael_sdk-0.0.2.dist-info/RECORD
