Metadata-Version: 2.1
Name: michael-sdk
Version: 0.0.2
Summary: Python API SDK to integrate you with The One API
Home-page: https://github.com/aluminiumgeek/michael-sdk
Author: Mikhail Mezyakov
Author-email: mihail265@gmail.com
License: MIT
Keywords: The One API,SDK
Platform: UNKNOWN
Classifier: Programming Language :: Python :: 3
Classifier: License :: OSI Approved :: MIT License
Classifier: Operating System :: OS Independent
License-File: LICENSE
Requires-Dist: requests (==2.27.1)
